pru/__init__.py
pru/cli.py
pru/core.py
pru/version.py
pru-0.0.4.dist-info/licenses/LICENSE
pru-0.0.4.dist-info/METADATA
pru-0.0.4.dist-info/WHEEL
pru-0.0.4.dist-info/entry_points.txt
pru-0.0.4.dist-info/top_level.txt
pru-0.0.4.dist-info/RECORD
