Metadata-Version: 2.4
Name: pru
Version: 0.0.4
Summary: Update and resolve requirements.txt based on the Python environment and pip used.
Author-email: Muhammad Yasirroni <muhammadyasirroni@gmail.com>
Maintainer-email: Muhammad Yasirroni <muhammadyasirroni@gmail.com>
Project-URL: Documentation, https://github.com/yasirroni/pru#readme
Project-URL: Issues, https://github.com/yasirroni/pru/issues
Project-URL: Source, https://github.com/yasirroni/pru
Classifier: Programming Language :: Python
Classifier: Programming Language :: Python :: 3.7
Classifier: Programming Language :: Python :: 3.8
Classifier: Programming Language :: Python :: 3.9
Classifier: Programming Language :: Python :: 3.10
Classifier: Programming Language :: Python :: 3.11
Classifier: Programming Language :: Python :: 3.12
Classifier: Programming Language :: Python :: 3.13
Requires-Python: >=3.7.1
License-File: LICENSE
Provides-Extra: dev
Requires-Dist: pytest>=7.2.0; extra == "dev"
Requires-Dist: pytest-cov>=4.1.0; extra == "dev"
Requires-Dist: pytest-xdist>=3.1.0; extra == "dev"
Requires-Dist: pre-commit>=2.21.0; extra == "dev"
Requires-Dist: ruff>=0.0.254; extra == "dev"
Requires-Dist: setuptools>=68.0.0; extra == "dev"
Requires-Dist: pytest-cov>=4.1.0; extra == "dev"
Requires-Dist: pytest-dependency>=0.5.1; extra == "dev"
Dynamic: license-file
